duple/.DS_Store
duple/__app_name__.py
duple/__version__.py
duple/app_logging.py
duple/decorators.py
duple/dispocode.py
duple/duple.py
duple/file.py
duple/files.py
duple/info.py
duple/library.py
duple/logging_configuration.json
duple/logging_formatter.py
duple/logs/log.jsonl
duple/logs/log.log
duple/status.py
duple-2.1.7.dist-info/LICENSE
duple-2.1.7.dist-info/METADATA
duple-2.1.7.dist-info/WHEEL
duple-2.1.7.dist-info/entry_points.txt
duple-2.1.7.dist-info/RECORD
