Metadata-Version: 2.1
Name: duple
Version: 2.1.7
Summary: Duple is a CLI that finds and removes duplicate files.
Home-page: https://github.com/dbruce-ae05/duple
License: GPL-3.0-or-later
Keywords: duplicate,lint
Author: David Bruce
Author-email: duple.python@gmail.com
Requires-Python: >=3.11,<4.0
Classifier: License :: OSI Approved :: GNU General Public License v3 or later (GPLv3+)
Classifier: Programming Language :: Python :: 3
Classifier: Programming Language :: Python :: 3.11
Classifier: Programming Language :: Python :: 3.12
Classifier: Programming Language :: Python :: 3.13
Requires-Dist: click (>=8.1.7,<9.0.0)
Requires-Dist: humanize (>=4.10.0,<5.0.0)
Requires-Dist: psutil (>=6.0.0,<7.0.0)
Requires-Dist: send2trash (>=1.8.3,<2.0.0)
Requires-Dist: tqdm (>=4.66.5,<5.0.0)
Project-URL: Repository, https://github.com/dbruce-ae05/duple
